.gitignore
LICENSE
MANIFEST.in
README.md
pybaccarat.dox
setup.py
bin/historical.py
bin/isaw135k.py
bin/play_baccarat.py
bin/play_baccarat_interactive.py
bin/silver.py
docs/html/annotated.html
docs/html/bc_s.png
docs/html/bdwn.png
docs/html/classes.html
docs/html/classpybaccarat_1_1baccarat_1_1_game-members.html
docs/html/classpybaccarat_1_1baccarat_1_1_game.html
docs/html/classpybaccarat_1_1baccarat_1_1_game.png
docs/html/classpybaccarat_1_1baccarat_1_1_hand-members.html
docs/html/classpybaccarat_1_1baccarat_1_1_hand.html
docs/html/classpybaccarat_1_1baccarat_1_1_hand.png
docs/html/classpybaccarat_1_1baccarat_1_1_scoreboard-members.html
docs/html/classpybaccarat_1_1baccarat_1_1_scoreboard.html
docs/html/classpybaccarat_1_1baccarat_1_1_scoreboard.png
docs/html/classpybaccarat_1_1baccarat_1_1_ties-members.html
docs/html/classpybaccarat_1_1baccarat_1_1_ties.html
docs/html/classpybaccarat_1_1baccarat_1_1_ties.png
docs/html/classpybaccarat_1_1baccaratsystems_1_1_bacc_sys-members.html
docs/html/classpybaccarat_1_1baccaratsystems_1_1_bacc_sys.html
docs/html/classpybaccarat_1_1baccaratsystems_1_1_bacc_sys.png
docs/html/classpybaccarat_1_1baccaratsystems_1_1_dragon-members.html
docs/html/classpybaccarat_1_1baccaratsystems_1_1_dragon.html
docs/html/classpybaccarat_1_1baccaratsystems_1_1_dragon.png
docs/html/classpybaccarat_1_1baccaratsystems_1_1_e_z_dragon-members.html
docs/html/classpybaccarat_1_1baccaratsystems_1_1_e_z_dragon.html
docs/html/classpybaccarat_1_1baccaratsystems_1_1_e_z_dragon.png
docs/html/classpybaccarat_1_1baccaratsystems_1_1_val_sys-members.html
docs/html/classpybaccarat_1_1baccaratsystems_1_1_val_sys.html
docs/html/classpybaccarat_1_1baccaratsystems_1_1_val_sys.png
docs/html/classpybaccarat_1_1baccaratsystems_1_1interactive-members.html
docs/html/classpybaccarat_1_1baccaratsystems_1_1interactive.html
docs/html/classpybaccarat_1_1baccaratsystems_1_1interactive.png
docs/html/classpybaccarat_1_1playingcards_1_1_card-members.html
pybaccarat.egg-info/PKG-INFO
pybaccarat.egg-info/SOURCES.txt
pybaccarat.egg-info/dependency_links.txt
pybaccarat.egg-info/not-zip-safe
pybaccarat.egg-info/top_level.txt
