Metadata-Version: 1.1
Name: pybaccarat
Version: 0.18
Summary: Play the card game Baccarat
Home-page: https://github.com/fulkgl/PyBaccarat
Author: George L Fulk
Author-email: fulkgl@gmail.com
License: MIT
Download-URL: https://pypi.python.org/packages/source/P/pybaccarat/pybaccarat-0.18.tar.gz
Keywords: baccarat,game,playing cards,cards,card game
Platform: UNKNOWN
Classifier: Development Status :: 3 - Alpha
Classifier: Environment :: Console
Classifier: License :: OSI Approved :: MIT License
Classifier: Natural Language :: English
Classifier: Operating System :: OS Independent
Classifier: Programming Language :: Python
Classifier: Programming Language :: Python :: 2
Classifier: Programming Language :: Python :: 2.7
Classifier: Programming Language :: Python :: 3
Classifier: Programming Language :: Python :: 3.6
Classifier: Topic :: Games/Entertainment
Classifier: Topic :: Software Development :: Libraries :: Python Modules
